Metadata-Version: 1.0
Name: telecomanalyz
Version: 0.1.2
Summary: analyz job for telecom
Home-page: https://github.com/cuisidong/Demon
Author: cuisidong
Author-email: 18605629932@wo.com.cn
License: MIT
Platform: UNKNOWN
